LICENSE
MANIFEST.in
requirements.txt
setup.cfg
setup.py
test_requirements.txt
eth_faucet/__init__.py
eth_faucet/faucet.py
eth_faucet/period.py
eth_faucet.egg-info/PKG-INFO
eth_faucet.egg-info/SOURCES.txt
eth_faucet.egg-info/dependency_links.txt
eth_faucet.egg-info/entry_points.txt
eth_faucet.egg-info/requires.txt
eth_faucet.egg-info/top_level.txt
eth_faucet/data/EthFaucet.bin
eth_faucet/data/EthFaucet.json
eth_faucet/data/EthFaucet.metadata.json
eth_faucet/data/PeriodSimple.bin
eth_faucet/data/PeriodSimple.json
eth_faucet/data/PeriodSimple.metadata.json
eth_faucet/runnable/gen.py
eth_faucet/runnable/publish.py
tests/test_basic.py
tests/test_check.py
tests/test_period.py
tests/test_registry.py