Metadata-Version: 2.1
Name: eth-faucet
Version: 0.3.4
Summary: Gas token gifter with controls from time intervals, amounts and access.
Home-page: https://git.defalsify.org/eth-faucet
Author: Louis Holbrook
Author-email: dev@holbrook.no
License: AGPLv3+
Keywords: ethereum
Classifier: Programming Language :: Python :: 3
Classifier: Operating System :: OS Independent
Classifier: Development Status :: 4 - Beta
Classifier: Environment :: Console
Classifier: Intended Audience :: Developers
Classifier: License :: OSI Approved :: GNU Affero General Public License v3 or later (AGPLv3+)
Classifier: Topic :: Internet
Classifier: Topic :: Software Development :: Libraries
Requires-Python: >=3.8
Provides-Extra: testing
License-File: LICENSE
